MANIFEST.in
README
setup.py
src/canari/__init__.py
src/canari/__init__.pyc
src/canari/config.py
src/canari/easygui.py
src/canari/entrypoints.py
src/canari/framework.py
src/canari/mode.py
src/canari/project.py
src/canari/question.py
src/canari/resource.py
src/canari.egg-info/PKG-INFO
src/canari.egg-info/SOURCES.txt
src/canari.egg-info/dependency_links.txt
src/canari.egg-info/entry_points.txt
src/canari.egg-info/not-zip-safe
src/canari.egg-info/requires.txt
src/canari.egg-info/top_level.txt
src/canari/commands/__init__.py
src/canari/commands/banner.py
src/canari/commands/common.py
src/canari/commands/create_aws_lambda.py
src/canari/commands/create_package.py
src/canari/commands/create_profile.py
src/canari/commands/create_transform.py
src/canari/commands/debug_transform.py
src/canari/commands/dockerize_package.py
src/canari/commands/framework.py
src/canari/commands/generate_entities.py
src/canari/commands/generate_entities_doc.py
src/canari/commands/install_plume.py
src/canari/commands/list_transforms.py
src/canari/commands/load_plume_package.py
src/canari/commands/remote_transform.py
src/canari/commands/run_transform.py
src/canari/commands/shell.py
src/canari/commands/unload_plume_package.py
src/canari/commands/version.py
src/canari/maltego/__init__.py
src/canari/maltego/configuration.py
src/canari/maltego/entities.py
src/canari/maltego/message.py
src/canari/maltego/oxml.py
src/canari/maltego/runner.py
src/canari/maltego/transform.py
src/canari/maltego/utils.py
src/canari/pkgutils/__init__.py
src/canari/pkgutils/maltego.py
src/canari/pkgutils/transform.py
src/canari/resources/__init__.py
src/canari/resources/etc/__init__.py
src/canari/resources/etc/canari.conf
src/canari/resources/external/__init__.py
src/canari/resources/external/banner.txt
src/canari/resources/templates/__init__.py
src/canari/resources/templates/create_aws_lambda/.gitignore
src/canari/resources/templates/create_aws_lambda/.mrbob.ini
src/canari/resources/templates/create_aws_lambda/README
src/canari/resources/templates/create_aws_lambda/app.py.bob
src/canari/resources/templates/create_aws_lambda/requirements.txt.bob
src/canari/resources/templates/create_aws_lambda/.chalice/config.json.bob
